vpn/__init__.py
vpn/all.py
vpn/exceptions.py
vpn/ip.py
vpn/logger.py
vpn/process.py
vpn/utils.py
vpn/windows_cui.py
vpn/windows_gui.py
openvpn_tools-0.0.2.dist-info/LICENSE
openvpn_tools-0.0.2.dist-info/METADATA
openvpn_tools-0.0.2.dist-info/WHEEL
openvpn_tools-0.0.2.dist-info/top_level.txt
openvpn_tools-0.0.2.dist-info/RECORD
