Metadata-Version: 2.1
Name: openvpn-tools
Version: 0.0.2
Summary: Cross-platform openvpn tools
Home-page: https://github.com/sandbox-pokhara/openvpn-tools
Author: Pradish Bijukchhe
Author-email: pradishbijukchhe@gmail.com
License: UNKNOWN
Project-URL: Bug Tracker, https://github.com/sandbox-pokhara/openvpn-tools/issues
Platform: UNKNOWN
Classifier: Programming Language :: Python :: 3
Classifier: License :: OSI Approved :: MIT License
Classifier: Operating System :: OS Independent
Requires-Python: >=3.6
License-File: LICENSE
Requires-Dist: psutil
